cddd_onnx/__init__.py
cddd_onnx/main.py
cddd_onnx/model_downloader.py
cddd_onnx/preprocessing.py
cddd_onnx/tokenizer.py
cddd_onnx-0.1.0.dist-info/METADATA
cddd_onnx-0.1.0.dist-info/WHEEL
cddd_onnx-0.1.0.dist-info/entry_points.txt
cddd_onnx-0.1.0.dist-info/RECORD
