Metadata-Version: 2.4
Name: cddd-onnx
Version: 0.1.0
Summary: CDDD models in ONNX format with automatic model downloading
Project-URL: Homepage, https://github.com/sergsb/cddd-onnx
Project-URL: Bug Tracker, https://github.com/sergsb/cddd-onnx/issues
Author-email: Sergey Sosnin <sergey.sosnin@univie.ac.at>
Classifier: Environment :: Console
Classifier: Intended Audience :: Science/Research
Classifier: License :: OSI Approved :: MIT License
Classifier: Operating System :: OS Independent
Classifier: Programming Language :: Python :: 3
Classifier: Topic :: Scientific/Engineering :: Artificial Intelligence
Classifier: Topic :: Scientific/Engineering :: Chemistry
Requires-Python: >=3.8
Requires-Dist: numpy
Requires-Dist: onnxruntime
Requires-Dist: pandas
Requires-Dist: rdkit
Requires-Dist: requests
Requires-Dist: tqdm
Provides-Extra: dev
Requires-Dist: pytest; extra == 'dev'
Requires-Dist: pytest-cov; extra == 'dev'
